findmfpy-0.1.0.dist-info/RECORD
findmfpy-0.1.0.dist-info/METADATA
findmfpy-0.1.0.dist-info/WHEEL
findmfpy-0.1.0.dist-info/licenses/LICENSE
findmfpy.libs/libstdc++-496613c0.so.6.0.32
findmfpy.libs/libgcc_s-a3a07607.so.1
findmfpy/_core.cpython-313-x86_64-linux-musl.so
findmfpy/_core.pyi
findmfpy/__init__.py
findmfpy/_api.py
findmfpy/py.typed
