Metadata-Version: 2.1
Name: findmfpy
Version: 0.1.0
Summary: Python bindings to findMF
Author-Email: Leonardo Schwarz <leonardo.schwarz@fgcz.ethz.ch>
License: BSD 3-Clause License
Classifier: Development Status :: 1 - Planning
Classifier: Intended Audience :: Science/Research
Classifier: Intended Audience :: Developers
Classifier: License :: OSI Approved :: BSD License
Classifier: Operating System :: OS Independent
Classifier: Programming Language :: Python
Classifier: Programming Language :: Python :: 3
Classifier: Programming Language :: Python :: 3 :: Only
Classifier: Programming Language :: Python :: 3.9
Classifier: Programming Language :: Python :: 3.10
Classifier: Programming Language :: Python :: 3.11
Classifier: Programming Language :: Python :: 3.12
Classifier: Programming Language :: Python :: 3.13
Classifier: Topic :: Scientific/Engineering
Classifier: Typing :: Typed
Project-URL: Homepage, https://github.com/findMF/findMFPy
Project-URL: Bug tracker, https://github.com/findMF/findMFPy/issues
Project-URL: Discussions, https://github.com/findMF/findMFPy/discussions
Project-URL: Changelog, https://github.com/findMF/findMFPy/releases
Requires-Python: >=3.9
Requires-Dist: numpy
Requires-Dist: pytest>=6; extra == "test"
Requires-Dist: pytest-cov>=3; extra == "test"
Requires-Dist: mkdocs; extra == "docs"
Requires-Dist: mkdocs-material; extra == "docs"
Requires-Dist: mkdocstrings[python]; extra == "docs"
Requires-Dist: black; extra == "docs"
Requires-Dist: findMFPy[docs,test]; extra == "dev"
Requires-Dist: nox; extra == "dev"
Provides-Extra: test
Provides-Extra: docs
Provides-Extra: dev
